isbnlib/__init__.py
isbnlib/_core.py
isbnlib/_cover.py
isbnlib/_desc.py
isbnlib/_doitotex.py
isbnlib/_dwords.py
isbnlib/_editions.py
isbnlib/_exceptions.py
isbnlib/_ext.py
isbnlib/_goob.py
isbnlib/_goom.py
isbnlib/_imcache.py
isbnlib/_infogroup.py
isbnlib/_isbn.py
isbnlib/_metadata.py
isbnlib/_msk.py
isbnlib/_oclc.py
isbnlib/_openl.py
isbnlib/_openled.py
isbnlib/_thinged.py
isbnlib/_wiki.py
isbnlib/_wikied.py
isbnlib/config.py
isbnlib/registry.py
isbnlib/_data/__init__.py
isbnlib/_data/data4info.py
isbnlib/_data/data4infoold.py
isbnlib/_data/data4mask.py
isbnlib/_data/data4maskold.py
isbnlib/_data/generate.py
isbnlib/dev/__init__.py
isbnlib/dev/_data.py
isbnlib/dev/_decorators.py
isbnlib/dev/_exceptions.py
isbnlib/dev/_files.py
isbnlib/dev/_fmt.py
isbnlib/dev/_helpers.py
isbnlib/dev/helpers.py
isbnlib/dev/vias.py
isbnlib/dev/webquery.py
isbnlib/dev/webservice.py
isbnlib2-3.11.2.dist-info/licenses/AUTHORS.md
isbnlib2-3.11.2.dist-info/licenses/COPYRIGHT.txt
isbnlib2-3.11.2.dist-info/licenses/LICENSE-LGPL-3.0.txt
isbnlib2-3.11.2.dist-info/METADATA
isbnlib2-3.11.2.dist-info/WHEEL
isbnlib2-3.11.2.dist-info/top_level.txt
isbnlib2-3.11.2.dist-info/RECORD
