Metadata-Version: 2.4
Name: isbnlib2
Version: 3.11.2
Summary: Extract, clean, transform, hyphenate and metadata for ISBNs (International Standard Book Number).
Author-email: Alexandre Lima Conde <xlcnd@outlook.com>, Hans-Fritz Pommes <valarmmail@gmx.de>
Maintainer-email: Hans-Fritz Pommes <valarmmail@gmx.de>
License-Expression: LGPL-3.0-only
Project-URL: Homepage, https://github.com/hans-fritz-pommes/isbnlib
Project-URL: Repository, https://github.com/hans-fritz-pommes/isbnlib.git
Project-URL: Issues, https://github.com/hans-fritz-pommes/isbnlib/issues
Project-URL: Changelog, https://github.com/hans-fritz-pommes/isbnlib/blob/dev/CHANGES.txt
Keywords: isbn,isbnlib,book,metadata
Classifier: Programming Language :: Python
Classifier: Programming Language :: Python :: 3
Classifier: Programming Language :: Python :: 3.9
Classifier: Programming Language :: Python :: 3.10
Classifier: Programming Language :: Python :: 3.11
Classifier: Programming Language :: Python :: 3.12
Classifier: Programming Language :: Python :: 3.13
Classifier: Operating System :: OS Independent
Classifier: Development Status :: 5 - Production/Stable
Classifier: Intended Audience :: Developers
Classifier: Topic :: Text Processing :: General
Classifier: Topic :: Software Development :: Libraries :: Python Modules
Requires-Python: >3.8
License-File: LICENSE-LGPL-3.0.txt
License-File: AUTHORS.md
License-File: COPYRIGHT.txt
Dynamic: license-file
